shetranio/__init__.py
shetranio/dem.py
shetranio/hdf.py
shetranio/model.py
shetranio/plan.py
shetranio/setup/__init__.py
shetranio/setup/gear.py
shetranio/setup/library.py
shetranio/setup/mask.py
shetranio/setup/run.py
shetranio/setup/setup.py
shetranio-0.4.1.dist-info/LICENSE
shetranio-0.4.1.dist-info/METADATA
shetranio-0.4.1.dist-info/WHEEL
shetranio-0.4.1.dist-info/top_level.txt
shetranio-0.4.1.dist-info/RECORD
